mqt/syrec/__init__.py
mqt/syrec/_version.py
mqt/syrec/_version.pyi
mqt/syrec/py.typed
mqt/syrec/pysyrec.cpython-310-x86_64-linux-gnu.so
mqt/syrec/syrec_editor.py
mqt_syrec-2.0.0.dist-info/METADATA
mqt_syrec-2.0.0.dist-info/WHEEL
mqt_syrec-2.0.0.dist-info/entry_points.txt
mqt_syrec-2.0.0.dist-info/RECORD
mqt_syrec-2.0.0.dist-info/licenses/LICENSE.md
