Metadata-Version: 2.4
Name: mqt.syrec
Version: 2.0.0
Summary: MQT SyReC Synthesizer: A Tool for HDL-based Synthesis of Reversible Circuits
Keywords: MQT,reversible-computing,design-automation,synthesis
Author-Email: Lukas Burgholzer <lukas.burgholzer@tum.de>, Smaran Adarsh <smaran.adarsh@tum.de>
License-Expression: MIT
License-File: LICENSE.md
Classifier: Development Status :: 4 - Beta
Classifier: Intended Audience :: Science/Research
Classifier: Natural Language :: English
Classifier: Operating System :: POSIX :: Linux
Classifier: Operating System :: MacOS
Classifier: Operating System :: Microsoft :: Windows
Classifier: Programming Language :: C++
Classifier: Programming Language :: Python
Classifier: Programming Language :: Python :: 3
Classifier: Programming Language :: Python :: 3 :: Only
Classifier: Programming Language :: Python :: 3.10
Classifier: Programming Language :: Python :: 3.11
Classifier: Programming Language :: Python :: 3.12
Classifier: Programming Language :: Python :: 3.13
Classifier: Programming Language :: Python :: 3.14
Classifier: Topic :: Scientific/Engineering :: Electronic Design Automation (EDA)
Classifier: Typing :: Typed
Project-URL: Homepage, https://github.com/munich-quantum-toolkit/syrec
Project-URL: Documentation, https://mqt.readthedocs.io/projects/syrec
Project-URL: Issues, https://github.com/munich-quantum-toolkit/syrec/issues
Project-URL: Discussions, https://github.com/munich-quantum-toolkit/syrec/discussions
Requires-Python: >=3.10
Requires-Dist: mqt.core~=3.3.1
Requires-Dist: PyQt6>=6.8
